SFOpenBoson-0.3.0.dist-info/DESCRIPTION.rst
SFOpenBoson-0.3.0.dist-info/METADATA
SFOpenBoson-0.3.0.dist-info/RECORD
SFOpenBoson-0.3.0.dist-info/WHEEL
SFOpenBoson-0.3.0.dist-info/metadata.json
SFOpenBoson-0.3.0.dist-info/top_level.txt
sfopenboson/__init__.py
sfopenboson/_version.py
sfopenboson/auxillary.py
sfopenboson/ops.py
sfopenboson/hamiltonians/__init__.py
sfopenboson/hamiltonians/gates.py
sfopenboson/tests/__init__.py
sfopenboson/tests/conftest.py
sfopenboson/tests/test_auxillary.py
sfopenboson/tests/test_bose_hubbard_prop.py
sfopenboson/tests/test_gates.py
sfopenboson/tests/test_gaussian_prop.py
